{
  "id": "b47ac10b-58cc-4372-a567-0e02b2c3d481",
  "created_at": "2025-01-15T10:00:00Z",
  "updated_at": "2025-01-15T10:00:00Z",
  "is_active": true,
  "sort_order": 55,
  "slug": "exercise-progression-principles",
  "content_category_id": "exercise-fundamentals",
  "day": 55,
  "lede_image": {
    "path": "/images/knowledge-base/b47ac10b-58cc-4372-a567-0e02b2c3d481/lede-progression-stairs.png",
    "description": "A split image showing a beginner doing wall push-ups on the left progressing to standard push-ups on the right, with gradual steps illustrated between them",
    "width": 1200,
    "height": 630,
    "prompt_generation_string": "Fitness progression visualization showing 5 stages of push-up progression from wall push-ups to full push-ups, clean minimalist style with arrows showing progression, bright motivating colors, photorealistic fitness illustration"
  },
  "title": "From Zero to Hero: Smart Exercise Progression Strategies",
  "body": "# From Zero to Hero: Smart Exercise Progression Strategies\n\nYou've probably seen those \"30-day transformation\" posts where someone goes from couch potato to CrossFit champion overnight. Here's the truth: real, sustainable progress happens through smart, systematic progression—not dramatic leaps that leave you injured or burned out.\n\n## The Progressive Overload Principle: Your North Star\n\nAt the heart of all exercise progression lies one fundamental concept: progressive overload. This simply means gradually increasing the demands on your body over time. Think of it like learning to read—you didn't jump straight from the alphabet to Shakespeare.\n\n![Progressive overload pyramid showing different methods](/images/knowledge-base/b47ac10b-58cc-4372-a567-0e02b2c3d481/overload-pyramid.png)\n\nYour body adapts to whatever you consistently ask it to do. If you do the same workout forever, you'll maintain your current fitness but won't improve. The magic happens when you nudge just slightly beyond your comfort zone—emphasis on *slightly*.\n\n## The Five Pillars of Smart Progression\n\n### 1. **Volume Progression (Do More)**\nThis is often the safest starting point for beginners:\n- Week 1: 2 sets of 8 squats\n- Week 3: 3 sets of 8 squats\n- Week 5: 3 sets of 10 squats\n\nVolume increases should be gradual—aim for no more than 10% increase per week. If you walked 2,000 steps yesterday, don't jump to 10,000 tomorrow. Try 2,200 instead.\n\n### 2. **Intensity Progression (Work Harder)**\nThis means making the exercise itself more challenging:\n- Use heavier weights\n- Move to a harder exercise variation\n- Increase the speed or power of movement\n\n![Exercise variation ladder showing squat progressions](/images/knowledge-base/b47ac10b-58cc-4372-a567-0e02b2c3d481/squat-progression-ladder.png)\n\n**Example Squat Progression:**\n1. Chair squats (sitting and standing)\n2. Box squats (controlled descent to a surface)\n3. Bodyweight squats\n4. Goblet squats (holding weight at chest)\n5. Barbell back squats\n\n### 3. **Frequency Progression (Do It More Often)**\nGradually increasing how often you exercise:\n- Month 1: Exercise 2 days per week\n- Month 2: Exercise 3 days per week\n- Month 3: Exercise 3-4 days per week\n\nRemember: more isn't always better. Recovery is when you actually get stronger.\n\n### 4. **Density Progression (Do More in Less Time)**\nThis involves completing the same work in less time:\n- Week 1: Complete workout in 45 minutes\n- Week 4: Complete same workout in 40 minutes\n- Week 8: Complete same workout in 35 minutes\n\nThis naturally happens as your fitness improves and you need less rest between exercises.\n\n### 5. **Complexity Progression (Master Then Advance)**\nStart with simple movements and gradually add complexity:\n- Master a regular plank before trying plank variations\n- Perfect bodyweight lunges before adding weight\n- Nail the push-up before attempting plyometric push-ups\n\n## The 2-Week Rule: Your Safety Net\n\n![2-week rule infographic with checkmarks](/images/knowledge-base/b47ac10b-58cc-4372-a567-0e02b2c3d481/two-week-rule.png)\n\nHere's a golden rule that will save you from injury and frustration: **Stay at each progression level for at least 2 weeks before advancing.** \n\nIf an exercise feels easy after one workout, resist the urge to immediately level up. Your muscles might be ready, but your connective tissues (tendons and ligaments) adapt more slowly. They need time to strengthen.\n\nSigns you're ready to progress:\n- Current workout feels genuinely easy (not just on a good day)\n- You can maintain perfect form throughout\n- No unusual soreness or fatigue afterward\n- You've consistently completed the workout for 2+ weeks\n\n## Regression Is Progression Too\n\nSometimes the smartest move is backward. If you're:\n- Returning from illness or injury\n- Experiencing unusual fatigue\n- Unable to maintain proper form\n- Feeling joint pain (not muscle soreness)\n\n...then scaling back is the progressive choice. Think of it as taking a running start to jump even higher.\n\n## The Percentage Method: Taking Guesswork Out\n\n![Percentage progression chart](/images/knowledge-base/b47ac10b-58cc-4372-a567-0e02b2c3d481/percentage-method.png)\n\nFor measurable progressions (weight, time, distance), use percentages:\n- **Conservative progression:** 5% increase every 2 weeks\n- **Moderate progression:** 10% increase every 2 weeks\n- **Aggressive progression:** 15% increase every 2 weeks (only for young, healthy beginners with perfect form)\n\nExample with weights:\n- Current: 20 lb dumbbells\n- Next progression (10%): 22 lbs\n- If 22 lbs unavailable, stay at 20 lbs but add 1-2 more reps\n\n## Exercise-Specific Progression Strategies\n\n### **Cardio Progression**\nFollow the F.I.T.T. principle:\n- **F**requency: Add one day per week every 2-3 weeks\n- **I**ntensity: Increase pace/resistance by 5% every 2 weeks\n- **T**ime: Add 5 minutes every 2 weeks\n- **T**ype: Vary between walking, cycling, swimming\n\nNever increase more than one variable at a time.\n\n### **Strength Training Progression**\n\n![Strength progression flowchart](/images/knowledge-base/b47ac10b-58cc-4372-a567-0e02b2c3d481/strength-flowchart.png)\n\n1. **Master bodyweight** (2-4 weeks)\n2. **Add light resistance** (2-4 weeks)\n3. **Increase weight by smallest increment** (every 2-3 weeks)\n4. **When stuck, add reps before adding weight**\n\nThe \"Two-Rep Rule\": When you can do 2 more reps than your target on your last set for two consecutive workouts, increase the weight.\n\n### **Flexibility Progression**\nOften overlooked but crucial:\n1. Hold stretches for 15 seconds → 30 seconds → 45 seconds\n2. Increase range of motion by 1-2 inches every week\n3. Progress from static → dynamic → loaded stretching\n\n## Common Progression Mistakes to Avoid\n\n### **The \"More Is Better\" Trap**\nDoing too much too soon is the fastest route to injury or burnout. Your enthusiasm is admirable, but your body needs time to adapt.\n\n### **The \"No Pain, No Gain\" Myth**\nMuscle burn during exercise? Normal. Sharp pain in joints? Stop immediately. Learn the difference between discomfort and damage.\n\n### **The Comparison Game**\nYour friend might progress faster. That Instagram influencer definitely started at a different fitness level. Your only competition is yesterday's you.\n\n### **Ignoring Recovery Needs**\nAs you progress, your recovery needs increase too. More intense workouts require better sleep, nutrition, and rest days.\n\n## Creating Your Personal Progression Plan\n\n![Personal progression template](/images/knowledge-base/b47ac10b-58cc-4372-a567-0e02b2c3d481/progression-template.png)\n\n1. **Pick your starting point** (be honest, not optimistic)\n2. **Choose ONE progression variable** to focus on for 2-4 weeks\n3. **Track your workouts** (phone notes are fine)\n4. **Assess every 2 weeks** (not daily)\n5. **Adjust based on how you feel**, not arbitrary timelines\n\n## The Long Game Mindset\n\nFitness progression isn't linear. You'll have weeks where you feel superhuman and weeks where everything feels heavy. This is normal. What matters is the overall trend over months, not daily fluctuations.\n\nThink of progression like growing a plant. You don't pull it up every day to check the roots. You water it consistently, give it appropriate light, and trust the process. Some weeks it seems dormant, then suddenly—growth spurt.\n\n## Your Progression Homework\n\nThis week, pick ONE exercise you're currently doing and apply ONE progression method:\n- If you're walking, add 5 minutes\n- If you're doing push-ups, try adding 2 more reps\n- If you're stretching, hold for 5 seconds longer\n\nDocument how it feels. In two weeks, reassess. This simple practice will teach you more about smart progression than any article ever could.\n\nRemember: Heroes aren't made overnight. They're built through thousands of small, smart progressions. Each workout where you do just a little bit more than last time is a victory. String enough of those victories together, and you'll be amazed where you end up.\n\nThe journey from zero to hero isn't about dramatic leaps—it's about consistent, intelligent steps forward. Your future fit self is built one smart progression at a time.",
  "tags": [
    "progression",
    "advancement",
    "strategy",
    "development",
    "growth"
  ],
  "learn_more_links": [
    {
      "type": "youtube_short",
      "url": "https://youtube.com/shorts/abc123prog",
      "title": "Progressive Overload in 60 Seconds",
      "description": "Quick visual guide to the 5 ways to progressively overload",
      "duration_seconds": 58
    },
    {
      "type": "blog",
      "url": "https://strongerbyscience.com/progressive-overload",
      "title": "The Complete Guide to Progressive Overload",
      "description": "Deep dive into the science of progression with practical examples"
    },
    {
      "type": "article",
      "url": "https://menshealth.com/beginner-progression",
      "title": "Beginner's Guide to Exercise Progression",
      "description": "Month-by-month progression plan for new exercisers"
    }
  ],
  "affiliate_links": [
    {
      "type": "amazon",
      "url": "https://amazon.com/workout-log-book/dp/B08XXX",
      "title": "Simple Workout Progress Tracker",
      "description": "Paper logbook to track your progression journey - no apps needed"
    },
    {
      "type": "amazon",
      "url": "https://amazon.com/resistance-bands-set/dp/B07YYY",
      "title": "Progressive Resistance Band Set",
      "description": "5 different resistance levels for perfect progression at home"
    },
    {
      "type": "other",
      "url": "https://roguefitness.com/fractional-plates",
      "title": "Fractional Weight Plates",
      "description": "Small weight increments (0.5-2.5 lbs) for gradual strength progression"
    }
  ],
  "image_urls": [
    {
      "path": "/images/knowledge-base/b47ac10b-58cc-4372-a567-0e02b2c3d481/overload-pyramid.png",
      "description": "Pyramid diagram showing 5 methods of progressive overload: volume at base, then intensity, frequency, density, and complexity at top",
      "width": 800,
      "height": 600,
      "prompt_generation_string": "Clean infographic pyramid showing progressive overload methods, modern fitness design, clear labels, professional training illustration"
    },
    {
      "path": "/images/knowledge-base/b47ac10b-58cc-4372-a567-0e02b2c3d481/squat-progression-ladder.png",
      "description": "Visual ladder showing 5 squat variations from easiest to hardest with stick figures demonstrating each",
      "width": 1000,
      "height": 400,
      "prompt_generation_string": "Horizontal progression ladder showing squat variations from chair squat to barbell squat, clean vector style, step by step illustration"
    },
    {
      "path": "/images/knowledge-base/b47ac10b-58cc-4372-a567-0e02b2c3d481/two-week-rule.png",
      "description": "Calendar infographic showing 2-week progression periods with checkmarks and safety reminders",
      "width": 800,
      "height": 500,
      "prompt_generation_string": "Calendar based infographic showing 2-week progression rule, safety focused design, checkmarks and progression indicators"
    },
    {
      "path": "/images/knowledge-base/b47ac10b-58cc-4372-a567-0e02b2c3d481/percentage-method.png",
      "description": "Chart showing conservative, moderate, and aggressive progression percentages with examples",
      "width": 900,
      "height": 500,
      "prompt_generation_string": "Clean percentage progression chart with three levels, examples with weights and reps, modern fitness infographic style"
    },
    {
      "path": "/images/knowledge-base/b47ac10b-58cc-4372-a567-0e02b2c3d481/strength-flowchart.png",
      "description": "Flowchart showing strength training progression path from bodyweight to weighted exercises",
      "width": 800,
      "height": 700,
      "prompt_generation_string": "Vertical flowchart showing strength progression pathway, decision points, clean design with arrows and exercise icons"
    },
    {
      "path": "/images/knowledge-base/b47ac10b-58cc-4372-a567-0e02b2c3d481/progression-template.png",
      "description": "Blank template showing how to plan personal progression with example filled in",
      "width": 800,
      "height": 600,
      "prompt_generation_string": "Workout progression planning template, partially filled example, clean notebook style design, motivational fitness planning tool"
    }
  ],
  "read_time": 5,
  "word_count": 1250,
  "key_takeaways": [
    "Progress by increasing only ONE variable at a time (volume, intensity, frequency, density, or complexity) and stay at each level for at least 2 weeks",
    "Use the 5-10% rule for measurable progressions and always prioritize perfect form over heavier weights or more reps",
    "Regression is sometimes the smartest progression—scaling back when needed prevents injury and enables long-term success"
  ],
  "passages": [
    {
      "id": "bb80ff25-5f16-45c4-adff-781a4e30b586",
      "title": "The Plateau Breakthrough",
      "passage_text": "Jordan stared at the weight rack, frustrated. Three weeks of the same 15-pound dumbbells for shoulder presses. \"Still stuck?\" asked Marcus, the gym regular who always seemed to know what he was doing.\n\n\"Yeah, 20 pounds feels impossible, but 15 is getting too easy,\" Jordan admitted.\n\nMarcus smiled knowingly. \"Try this—stick with 15 pounds but add two more reps to each set for the next two weeks. Then, do your regular reps with 17.5 pounds for two weeks. By the time you try 20s again, they'll feel manageable.\"\n\n\"That seems so slow though,\" Jordan protested.\n\n\"I've been training for five years,\" Marcus replied. \"The people who are still here after year one? They're the ones who progressed slowly. The ones who jumped weight too fast? They're nursing injuries at home.\"\n\nTwo months later, Jordan was pressing 22.5-pound dumbbells with perfect form, finally understanding that small steps forward beat giant leaps backward every time.",
      "image_urls": []
    },
    {
      "id": "acd2c94c-2931-4e2b-8c08-f2a7b4b7f032",
      "title": "The Comeback Strategy",
      "passage_text": "Mike hadn't exercised in three weeks due to a nasty flu. Standing in his home gym, he debated: jump back to where he left off, or start over?\n\n![Home gym setup with progression notes on whiteboard](/images/knowledge-base/b47ac10b-58cc-4372-a567-0e02b2c3d481/comeback-whiteboard.png)\n\nHe remembered his physical therapist's advice from his last injury: 'The 50% rule—after any break longer than a week, return at 50% of your previous intensity and build back up.'\n\nWeek 1 back: Half his usual weight, half his usual sets. It felt embarrassingly easy.\nWeek 2: 75% of his pre-illness workout. Starting to feel normal.\nWeek 3: Back to full strength, actually feeling stronger than before.\n\nHis workout journal entry that day read: 'Lesson learned—the ego wants to rush back, but the body rewards patience. Regression really is progression in disguise.'",
      "image_urls": [
        {
          "path": "/images/knowledge-base/b47ac10b-58cc-4372-a567-0e02b2c3d481/comeback-whiteboard.png",
          "description": "Home gym whiteboard showing the 50% comeback rule with weekly progression percentages written out",
          "width": 600,
          "height": 400,
          "prompt_generation_string": "Home gym whiteboard with comeback progression plan written out, 50% rule explained, clean organized notes, motivational fitness planning"
        }
      ]
    },
    {
      "id": "a954c269-b69a-47ac-9eaf-81d5bd41312b",
      "title": "Family Fitness Evolution",
      "passage_text": "Emma watched her 8-year-old daughter struggle with a full push-up during their family workout time. \"Mom, I can't do it!\"\n\n\"Let's make it a game,\" Emma suggested, remembering her own progression journey. \"Level 1 is wall push-ups—like giving the wall a high-five. Level 2 is on the stairs. Level 3 is on your knees. Level 4 is the full push-up you're trying.\"\n\nThey spent two weeks at each level, making it a family challenge. Emma's husband joined at Level 2, having his own shoulder limitations to work around.\n\nSix weeks later, her daughter completed her first full push-up, screaming \"Level 4 unlocked!\" The whole family celebrated, and Emma realized she'd taught her kids the most valuable fitness lesson: progress isn't about being perfect today—it's about being slightly better than yesterday.\n\nHer daughter now asks, \"What's the Level 1 version?\" whenever facing any challenge, fitness or otherwise.",
      "image_urls": []
    }
  ],
  "icon": "trending-up"
}